[{"path":"src/main/java/Duke.java","fileType":"java","lines":[{"lineNumber":1,"author":{"gitId":"yuhengr"},"content":"import java.util.Scanner;","lastModifiedDate":"2024-02-02"},{"lineNumber":2,"author":{"gitId":"yuhengr"},"content":"import java.io.FileNotFoundException;","lastModifiedDate":"2024-02-23"},{"lineNumber":3,"author":{"gitId":"yuhengr"},"content":"import java.io.IOException;","lastModifiedDate":"2024-02-23"},{"lineNumber":4,"author":{"gitId":"yuhengr"},"content":"import exception.EkudException;","lastModifiedDate":"2024-02-23"},{"lineNumber":5,"author":{"gitId":"yuhengr"},"content":"import task.TaskList;","lastModifiedDate":"2024-03-06"},{"lineNumber":6,"author":{"gitId":"yuhengr"},"content":"import storage.Storage;","lastModifiedDate":"2024-03-07"},{"lineNumber":7,"author":{"gitId":"yuhengr"},"content":"import ui.UI;","lastModifiedDate":"2024-03-07"},{"lineNumber":8,"author":{"gitId":"yuhengr"},"content":"","lastModifiedDate":"2024-02-02"},{"lineNumber":9,"author":{"gitId":"-"},"content":"public class Duke {","lastModifiedDate":"2019-07-29"},{"lineNumber":10,"author":{"gitId":"yuhengr"},"content":"","lastModifiedDate":"2024-02-23"},{"lineNumber":11,"author":{"gitId":"-"},"content":"    public static void main(String[] args) {","lastModifiedDate":"2019-07-29"},{"lineNumber":12,"author":{"gitId":"yuhengr"},"content":"","lastModifiedDate":"2024-03-07"},{"lineNumber":13,"author":{"gitId":"yuhengr"},"content":"        System.out.println(UI.GREETING_MESSAGE);","lastModifiedDate":"2024-03-07"},{"lineNumber":14,"author":{"gitId":"yuhengr"},"content":"","lastModifiedDate":"2024-02-02"},{"lineNumber":15,"author":{"gitId":"yuhengr"},"content":"        String userInput;","lastModifiedDate":"2024-02-02"},{"lineNumber":16,"author":{"gitId":"yuhengr"},"content":"        Scanner in \u003d new Scanner(System.in);","lastModifiedDate":"2024-02-02"},{"lineNumber":17,"author":{"gitId":"yuhengr"},"content":"        TaskList tasks \u003d new TaskList();","lastModifiedDate":"2024-03-06"},{"lineNumber":18,"author":{"gitId":"yuhengr"},"content":"","lastModifiedDate":"2024-02-23"},{"lineNumber":19,"author":{"gitId":"yuhengr"},"content":"        Storage storage \u003d new Storage();","lastModifiedDate":"2024-03-07"},{"lineNumber":20,"author":{"gitId":"yuhengr"},"content":"","lastModifiedDate":"2024-03-07"},{"lineNumber":21,"author":{"gitId":"yuhengr"},"content":"        try {","lastModifiedDate":"2024-02-23"},{"lineNumber":22,"author":{"gitId":"yuhengr"},"content":"            tasks \u003d storage.readFromFile();","lastModifiedDate":"2024-03-07"},{"lineNumber":23,"author":{"gitId":"yuhengr"},"content":"        }","lastModifiedDate":"2024-02-23"},{"lineNumber":24,"author":{"gitId":"yuhengr"},"content":"        catch (FileNotFoundException error){","lastModifiedDate":"2024-02-23"},{"lineNumber":25,"author":{"gitId":"yuhengr"},"content":"            System.out.println(UI.FILE_NOT_FOUND_MESSAGE);","lastModifiedDate":"2024-03-07"},{"lineNumber":26,"author":{"gitId":"yuhengr"},"content":"        }","lastModifiedDate":"2024-02-23"},{"lineNumber":27,"author":{"gitId":"yuhengr"},"content":"","lastModifiedDate":"2024-02-23"},{"lineNumber":28,"author":{"gitId":"yuhengr"},"content":"        userInput \u003d in.nextLine();","lastModifiedDate":"2024-02-02"},{"lineNumber":29,"author":{"gitId":"yuhengr"},"content":"","lastModifiedDate":"2024-02-02"},{"lineNumber":30,"author":{"gitId":"yuhengr"},"content":"        while(!userInput.equals(\"bye\")){","lastModifiedDate":"2024-02-02"},{"lineNumber":31,"author":{"gitId":"yuhengr"},"content":"            String[] userInputWords \u003d userInput.split(\" \");","lastModifiedDate":"2024-02-23"},{"lineNumber":32,"author":{"gitId":"yuhengr"},"content":"            String userCommand \u003d userInputWords[0].toLowerCase();","lastModifiedDate":"2024-03-08"},{"lineNumber":33,"author":{"gitId":"yuhengr"},"content":"","lastModifiedDate":"2024-02-23"},{"lineNumber":34,"author":{"gitId":"yuhengr"},"content":"            if(userCommand.equals(\"list\")){","lastModifiedDate":"2024-03-08"},{"lineNumber":35,"author":{"gitId":"yuhengr"},"content":"                tasks.list();","lastModifiedDate":"2024-03-06"},{"lineNumber":36,"author":{"gitId":"yuhengr"},"content":"            }","lastModifiedDate":"2024-02-09"},{"lineNumber":37,"author":{"gitId":"yuhengr"},"content":"            else if(userCommand.equals(\"mark\")){","lastModifiedDate":"2024-03-08"},{"lineNumber":38,"author":{"gitId":"yuhengr"},"content":"                tasks.mark(userInput);","lastModifiedDate":"2024-03-06"},{"lineNumber":39,"author":{"gitId":"yuhengr"},"content":"            }","lastModifiedDate":"2024-02-23"},{"lineNumber":40,"author":{"gitId":"yuhengr"},"content":"            else if(userCommand.equals(\"unmark\")){","lastModifiedDate":"2024-03-08"},{"lineNumber":41,"author":{"gitId":"yuhengr"},"content":"                tasks.unmark(userInput);","lastModifiedDate":"2024-03-06"},{"lineNumber":42,"author":{"gitId":"yuhengr"},"content":"            }","lastModifiedDate":"2024-02-23"},{"lineNumber":43,"author":{"gitId":"yuhengr"},"content":"            else if(userCommand.equals(\"todo\")){","lastModifiedDate":"2024-03-08"},{"lineNumber":44,"author":{"gitId":"yuhengr"},"content":"                tasks.addTodo(userInput);","lastModifiedDate":"2024-03-06"},{"lineNumber":45,"author":{"gitId":"yuhengr"},"content":"            }","lastModifiedDate":"2024-02-23"},{"lineNumber":46,"author":{"gitId":"yuhengr"},"content":"            else if(userCommand.equals(\"deadline\")){","lastModifiedDate":"2024-03-08"},{"lineNumber":47,"author":{"gitId":"yuhengr"},"content":"                tasks.addDeadline(userInput);","lastModifiedDate":"2024-03-06"},{"lineNumber":48,"author":{"gitId":"yuhengr"},"content":"            }","lastModifiedDate":"2024-02-23"},{"lineNumber":49,"author":{"gitId":"yuhengr"},"content":"            else if(userCommand.equals(\"event\")){","lastModifiedDate":"2024-03-08"},{"lineNumber":50,"author":{"gitId":"yuhengr"},"content":"                tasks.addEvent(userInput);","lastModifiedDate":"2024-03-06"},{"lineNumber":51,"author":{"gitId":"yuhengr"},"content":"            }","lastModifiedDate":"2024-02-23"},{"lineNumber":52,"author":{"gitId":"yuhengr"},"content":"            else if(userCommand.equals(\"delete\")){","lastModifiedDate":"2024-03-08"},{"lineNumber":53,"author":{"gitId":"yuhengr"},"content":"                tasks.delete(userInput);","lastModifiedDate":"2024-03-06"},{"lineNumber":54,"author":{"gitId":"yuhengr"},"content":"            }","lastModifiedDate":"2024-02-23"},{"lineNumber":55,"author":{"gitId":"yuhengr"},"content":"            else if(userCommand.equals(\"find\")) {","lastModifiedDate":"2024-03-08"},{"lineNumber":56,"author":{"gitId":"yuhengr"},"content":"                tasks.find(userInput);","lastModifiedDate":"2024-03-08"},{"lineNumber":57,"author":{"gitId":"yuhengr"},"content":"            }","lastModifiedDate":"2024-03-08"},{"lineNumber":58,"author":{"gitId":"yuhengr"},"content":"            else{","lastModifiedDate":"2024-02-09"},{"lineNumber":59,"author":{"gitId":"yuhengr"},"content":"                try {","lastModifiedDate":"2024-02-23"},{"lineNumber":60,"author":{"gitId":"yuhengr"},"content":"                    throw new EkudException();","lastModifiedDate":"2024-02-23"},{"lineNumber":61,"author":{"gitId":"yuhengr"},"content":"                }","lastModifiedDate":"2024-02-23"},{"lineNumber":62,"author":{"gitId":"yuhengr"},"content":"                catch (EkudException error){","lastModifiedDate":"2024-02-23"},{"lineNumber":63,"author":{"gitId":"yuhengr"},"content":"                    System.out.println(UI.INVALID_COMMAND_MESSAGE);","lastModifiedDate":"2024-03-07"},{"lineNumber":64,"author":{"gitId":"yuhengr"},"content":"                }","lastModifiedDate":"2024-02-23"},{"lineNumber":65,"author":{"gitId":"yuhengr"},"content":"            }","lastModifiedDate":"2024-02-09"},{"lineNumber":66,"author":{"gitId":"yuhengr"},"content":"            userInput \u003d in.nextLine();","lastModifiedDate":"2024-02-02"},{"lineNumber":67,"author":{"gitId":"yuhengr"},"content":"        }","lastModifiedDate":"2024-02-02"},{"lineNumber":68,"author":{"gitId":"yuhengr"},"content":"","lastModifiedDate":"2024-02-02"},{"lineNumber":69,"author":{"gitId":"yuhengr"},"content":"        try {","lastModifiedDate":"2024-03-07"},{"lineNumber":70,"author":{"gitId":"yuhengr"},"content":"            storage.writeToFile(tasks);","lastModifiedDate":"2024-03-07"},{"lineNumber":71,"author":{"gitId":"yuhengr"},"content":"        }","lastModifiedDate":"2024-03-07"},{"lineNumber":72,"author":{"gitId":"yuhengr"},"content":"        catch(IOException error) {","lastModifiedDate":"2024-03-07"},{"lineNumber":73,"author":{"gitId":"yuhengr"},"content":"            System.out.println(UI.FILE_WRITE_ERROR_MESSAGE);","lastModifiedDate":"2024-03-07"},{"lineNumber":74,"author":{"gitId":"yuhengr"},"content":"        }","lastModifiedDate":"2024-03-07"},{"lineNumber":75,"author":{"gitId":"yuhengr"},"content":"","lastModifiedDate":"2024-03-07"},{"lineNumber":76,"author":{"gitId":"yuhengr"},"content":"        System.out.println(UI.EXIT_MESSAGE);","lastModifiedDate":"2024-03-07"},{"lineNumber":77,"author":{"gitId":"-"},"content":"    }","lastModifiedDate":"2019-07-29"},{"lineNumber":78,"author":{"gitId":"-"},"content":"}","lastModifiedDate":"2019-07-29"}],"authorContributionMap":{"yuhengr":74,"-":4}},{"path":"src/main/java/exception/EkudException.java","fileType":"java","lines":[{"lineNumber":1,"author":{"gitId":"yuhengr"},"content":"package exception;","lastModifiedDate":"2024-02-23"},{"lineNumber":2,"author":{"gitId":"yuhengr"},"content":"","lastModifiedDate":"2024-02-23"},{"lineNumber":3,"author":{"gitId":"yuhengr"},"content":"public class EkudException extends Exception {","lastModifiedDate":"2024-02-23"},{"lineNumber":4,"author":{"gitId":"yuhengr"},"content":"}","lastModifiedDate":"2024-02-23"}],"authorContributionMap":{"yuhengr":4}},{"path":"src/main/java/storage/Storage.java","fileType":"java","lines":[{"lineNumber":1,"author":{"gitId":"yuhengr"},"content":"package storage;","lastModifiedDate":"2024-03-06"},{"lineNumber":2,"author":{"gitId":"yuhengr"},"content":"","lastModifiedDate":"2024-03-06"},{"lineNumber":3,"author":{"gitId":"yuhengr"},"content":"import java.util.Scanner;","lastModifiedDate":"2024-03-06"},{"lineNumber":4,"author":{"gitId":"yuhengr"},"content":"import java.io.File;","lastModifiedDate":"2024-03-06"},{"lineNumber":5,"author":{"gitId":"yuhengr"},"content":"import java.io.FileNotFoundException;","lastModifiedDate":"2024-03-06"},{"lineNumber":6,"author":{"gitId":"yuhengr"},"content":"import java.io.FileWriter;","lastModifiedDate":"2024-03-06"},{"lineNumber":7,"author":{"gitId":"yuhengr"},"content":"import java.io.IOException;","lastModifiedDate":"2024-03-06"},{"lineNumber":8,"author":{"gitId":"yuhengr"},"content":"import task.TaskList;","lastModifiedDate":"2024-03-07"},{"lineNumber":9,"author":{"gitId":"yuhengr"},"content":"","lastModifiedDate":"2024-03-06"},{"lineNumber":10,"author":{"gitId":"yuhengr"},"content":"public class Storage {","lastModifiedDate":"2024-03-06"},{"lineNumber":11,"author":{"gitId":"yuhengr"},"content":"","lastModifiedDate":"2024-03-06"},{"lineNumber":12,"author":{"gitId":"yuhengr"},"content":"    private static final String filePath \u003d \"tasks.txt\";","lastModifiedDate":"2024-03-06"},{"lineNumber":13,"author":{"gitId":"yuhengr"},"content":"","lastModifiedDate":"2024-03-06"},{"lineNumber":14,"author":{"gitId":"yuhengr"},"content":"    public Storage() {}","lastModifiedDate":"2024-03-07"},{"lineNumber":15,"author":{"gitId":"yuhengr"},"content":"","lastModifiedDate":"2024-03-06"},{"lineNumber":16,"author":{"gitId":"yuhengr"},"content":"    public void writeToFile(TaskList tasks) throws IOException {","lastModifiedDate":"2024-03-07"},{"lineNumber":17,"author":{"gitId":"yuhengr"},"content":"        FileWriter fw \u003d new FileWriter(filePath);","lastModifiedDate":"2024-03-07"},{"lineNumber":18,"author":{"gitId":"yuhengr"},"content":"        for(int i \u003d 0; i \u003c tasks.getTaskCount(); i++){","lastModifiedDate":"2024-03-07"},{"lineNumber":19,"author":{"gitId":"yuhengr"},"content":"            fw.write(tasks.getTask(i).toString() + \"\\n\");","lastModifiedDate":"2024-03-07"},{"lineNumber":20,"author":{"gitId":"yuhengr"},"content":"        }","lastModifiedDate":"2024-03-07"},{"lineNumber":21,"author":{"gitId":"yuhengr"},"content":"        fw.close();","lastModifiedDate":"2024-03-07"},{"lineNumber":22,"author":{"gitId":"yuhengr"},"content":"    };","lastModifiedDate":"2024-03-06"},{"lineNumber":23,"author":{"gitId":"yuhengr"},"content":"","lastModifiedDate":"2024-03-06"},{"lineNumber":24,"author":{"gitId":"yuhengr"},"content":"    public TaskList readFromFile() throws FileNotFoundException {","lastModifiedDate":"2024-03-07"},{"lineNumber":25,"author":{"gitId":"yuhengr"},"content":"        File f \u003d new File(filePath);","lastModifiedDate":"2024-03-07"},{"lineNumber":26,"author":{"gitId":"yuhengr"},"content":"        Scanner s \u003d new Scanner(f);","lastModifiedDate":"2024-03-07"},{"lineNumber":27,"author":{"gitId":"yuhengr"},"content":"        TaskList tasks \u003d new TaskList();","lastModifiedDate":"2024-03-07"},{"lineNumber":28,"author":{"gitId":"yuhengr"},"content":"        while(s.hasNext()) {","lastModifiedDate":"2024-03-07"},{"lineNumber":29,"author":{"gitId":"yuhengr"},"content":"            String currentLine \u003d s.nextLine();","lastModifiedDate":"2024-03-07"},{"lineNumber":30,"author":{"gitId":"yuhengr"},"content":"            tasks.addTaskFromFile(currentLine);","lastModifiedDate":"2024-03-07"},{"lineNumber":31,"author":{"gitId":"yuhengr"},"content":"        }","lastModifiedDate":"2024-03-07"},{"lineNumber":32,"author":{"gitId":"yuhengr"},"content":"        return tasks;","lastModifiedDate":"2024-03-07"},{"lineNumber":33,"author":{"gitId":"yuhengr"},"content":"    };","lastModifiedDate":"2024-03-06"},{"lineNumber":34,"author":{"gitId":"yuhengr"},"content":"}","lastModifiedDate":"2024-03-06"}],"authorContributionMap":{"yuhengr":34}},{"path":"src/main/java/task/Deadline.java","fileType":"java","lines":[{"lineNumber":1,"author":{"gitId":"yuhengr"},"content":"package task;","lastModifiedDate":"2024-03-06"},{"lineNumber":2,"author":{"gitId":"yuhengr"},"content":"","lastModifiedDate":"2024-03-06"},{"lineNumber":3,"author":{"gitId":"yuhengr"},"content":"public class Deadline extends Task {","lastModifiedDate":"2024-02-09"},{"lineNumber":4,"author":{"gitId":"yuhengr"},"content":"","lastModifiedDate":"2024-02-09"},{"lineNumber":5,"author":{"gitId":"yuhengr"},"content":"    protected String by;","lastModifiedDate":"2024-02-09"},{"lineNumber":6,"author":{"gitId":"yuhengr"},"content":"","lastModifiedDate":"2024-02-09"},{"lineNumber":7,"author":{"gitId":"yuhengr"},"content":"    public Deadline(String description, String by) {","lastModifiedDate":"2024-02-09"},{"lineNumber":8,"author":{"gitId":"yuhengr"},"content":"        super(description);","lastModifiedDate":"2024-02-09"},{"lineNumber":9,"author":{"gitId":"yuhengr"},"content":"        this.by \u003d by;","lastModifiedDate":"2024-02-09"},{"lineNumber":10,"author":{"gitId":"yuhengr"},"content":"    }","lastModifiedDate":"2024-02-09"},{"lineNumber":11,"author":{"gitId":"yuhengr"},"content":"","lastModifiedDate":"2024-02-09"},{"lineNumber":12,"author":{"gitId":"yuhengr"},"content":"    @Override","lastModifiedDate":"2024-02-09"},{"lineNumber":13,"author":{"gitId":"yuhengr"},"content":"    public String toString() {","lastModifiedDate":"2024-02-09"},{"lineNumber":14,"author":{"gitId":"yuhengr"},"content":"        return \"[D]\" + super.toString() + \" (by: \" + by + \")\";","lastModifiedDate":"2024-02-09"},{"lineNumber":15,"author":{"gitId":"yuhengr"},"content":"    }","lastModifiedDate":"2024-02-09"},{"lineNumber":16,"author":{"gitId":"yuhengr"},"content":"}","lastModifiedDate":"2024-02-09"}],"authorContributionMap":{"yuhengr":16}},{"path":"src/main/java/task/Event.java","fileType":"java","lines":[{"lineNumber":1,"author":{"gitId":"yuhengr"},"content":"package task;","lastModifiedDate":"2024-03-06"},{"lineNumber":2,"author":{"gitId":"yuhengr"},"content":"","lastModifiedDate":"2024-03-06"},{"lineNumber":3,"author":{"gitId":"yuhengr"},"content":"public class Event extends Task {","lastModifiedDate":"2024-02-09"},{"lineNumber":4,"author":{"gitId":"yuhengr"},"content":"","lastModifiedDate":"2024-02-09"},{"lineNumber":5,"author":{"gitId":"yuhengr"},"content":"    protected String startTime;","lastModifiedDate":"2024-02-09"},{"lineNumber":6,"author":{"gitId":"yuhengr"},"content":"    protected String endTime;","lastModifiedDate":"2024-02-09"},{"lineNumber":7,"author":{"gitId":"yuhengr"},"content":"","lastModifiedDate":"2024-02-09"},{"lineNumber":8,"author":{"gitId":"yuhengr"},"content":"    public Event(String description, String startTime, String endTime) {","lastModifiedDate":"2024-02-09"},{"lineNumber":9,"author":{"gitId":"yuhengr"},"content":"        super(description);","lastModifiedDate":"2024-02-09"},{"lineNumber":10,"author":{"gitId":"yuhengr"},"content":"        this.startTime \u003d startTime;","lastModifiedDate":"2024-02-09"},{"lineNumber":11,"author":{"gitId":"yuhengr"},"content":"        this.endTime \u003d endTime;","lastModifiedDate":"2024-02-09"},{"lineNumber":12,"author":{"gitId":"yuhengr"},"content":"    }","lastModifiedDate":"2024-02-09"},{"lineNumber":13,"author":{"gitId":"yuhengr"},"content":"","lastModifiedDate":"2024-02-09"},{"lineNumber":14,"author":{"gitId":"yuhengr"},"content":"    public String toString() {","lastModifiedDate":"2024-02-09"},{"lineNumber":15,"author":{"gitId":"yuhengr"},"content":"        return \"[E]\" + super.toString() + \" (from: \" + this.startTime + \" to: \" + this.endTime + \")\";","lastModifiedDate":"2024-02-09"},{"lineNumber":16,"author":{"gitId":"yuhengr"},"content":"    }","lastModifiedDate":"2024-02-09"},{"lineNumber":17,"author":{"gitId":"yuhengr"},"content":"}","lastModifiedDate":"2024-02-09"}],"authorContributionMap":{"yuhengr":17}},{"path":"src/main/java/task/Task.java","fileType":"java","lines":[{"lineNumber":1,"author":{"gitId":"yuhengr"},"content":"package task;","lastModifiedDate":"2024-03-06"},{"lineNumber":2,"author":{"gitId":"yuhengr"},"content":"","lastModifiedDate":"2024-03-06"},{"lineNumber":3,"author":{"gitId":"yuhengr"},"content":"public class Task {","lastModifiedDate":"2024-02-09"},{"lineNumber":4,"author":{"gitId":"yuhengr"},"content":"    protected String description;","lastModifiedDate":"2024-02-09"},{"lineNumber":5,"author":{"gitId":"yuhengr"},"content":"    protected boolean isDone;","lastModifiedDate":"2024-02-09"},{"lineNumber":6,"author":{"gitId":"yuhengr"},"content":"","lastModifiedDate":"2024-02-09"},{"lineNumber":7,"author":{"gitId":"yuhengr"},"content":"    public Task(String description) {","lastModifiedDate":"2024-02-09"},{"lineNumber":8,"author":{"gitId":"yuhengr"},"content":"        this.description \u003d description;","lastModifiedDate":"2024-02-09"},{"lineNumber":9,"author":{"gitId":"yuhengr"},"content":"        this.isDone \u003d false;","lastModifiedDate":"2024-02-09"},{"lineNumber":10,"author":{"gitId":"yuhengr"},"content":"    }","lastModifiedDate":"2024-02-09"},{"lineNumber":11,"author":{"gitId":"yuhengr"},"content":"","lastModifiedDate":"2024-02-09"},{"lineNumber":12,"author":{"gitId":"yuhengr"},"content":"    public String getStatusIcon() {","lastModifiedDate":"2024-02-09"},{"lineNumber":13,"author":{"gitId":"yuhengr"},"content":"        return (isDone ? \"X\" : \" \");","lastModifiedDate":"2024-02-09"},{"lineNumber":14,"author":{"gitId":"yuhengr"},"content":"    }","lastModifiedDate":"2024-02-09"},{"lineNumber":15,"author":{"gitId":"yuhengr"},"content":"","lastModifiedDate":"2024-02-09"},{"lineNumber":16,"author":{"gitId":"yuhengr"},"content":"    public void markAsDone() {","lastModifiedDate":"2024-02-09"},{"lineNumber":17,"author":{"gitId":"yuhengr"},"content":"        this.isDone \u003d true;","lastModifiedDate":"2024-02-09"},{"lineNumber":18,"author":{"gitId":"yuhengr"},"content":"    }","lastModifiedDate":"2024-02-09"},{"lineNumber":19,"author":{"gitId":"yuhengr"},"content":"","lastModifiedDate":"2024-02-09"},{"lineNumber":20,"author":{"gitId":"yuhengr"},"content":"    public void markAsNotDone() {","lastModifiedDate":"2024-02-09"},{"lineNumber":21,"author":{"gitId":"yuhengr"},"content":"        this.isDone \u003d false;","lastModifiedDate":"2024-02-09"},{"lineNumber":22,"author":{"gitId":"yuhengr"},"content":"    }","lastModifiedDate":"2024-02-09"},{"lineNumber":23,"author":{"gitId":"yuhengr"},"content":"","lastModifiedDate":"2024-02-09"},{"lineNumber":24,"author":{"gitId":"yuhengr"},"content":"    @Override","lastModifiedDate":"2024-02-09"},{"lineNumber":25,"author":{"gitId":"yuhengr"},"content":"    public String toString() {","lastModifiedDate":"2024-02-09"},{"lineNumber":26,"author":{"gitId":"yuhengr"},"content":"        return String.format(\"[%s] %s\", this.getStatusIcon(), this.description);","lastModifiedDate":"2024-02-09"},{"lineNumber":27,"author":{"gitId":"yuhengr"},"content":"    }","lastModifiedDate":"2024-02-09"},{"lineNumber":28,"author":{"gitId":"yuhengr"},"content":"}","lastModifiedDate":"2024-02-09"}],"authorContributionMap":{"yuhengr":28}},{"path":"src/main/java/task/TaskList.java","fileType":"java","lines":[{"lineNumber":1,"author":{"gitId":"yuhengr"},"content":"package task;","lastModifiedDate":"2024-03-06"},{"lineNumber":2,"author":{"gitId":"yuhengr"},"content":"","lastModifiedDate":"2024-03-06"},{"lineNumber":3,"author":{"gitId":"yuhengr"},"content":"import java.util.ArrayList;","lastModifiedDate":"2024-03-06"},{"lineNumber":4,"author":{"gitId":"yuhengr"},"content":"import exception.EkudException;","lastModifiedDate":"2024-03-06"},{"lineNumber":5,"author":{"gitId":"yuhengr"},"content":"import ui.UI;","lastModifiedDate":"2024-03-07"},{"lineNumber":6,"author":{"gitId":"yuhengr"},"content":"import ui.Parser;","lastModifiedDate":"2024-03-08"},{"lineNumber":7,"author":{"gitId":"yuhengr"},"content":"","lastModifiedDate":"2024-03-06"},{"lineNumber":8,"author":{"gitId":"yuhengr"},"content":"public class TaskList {","lastModifiedDate":"2024-03-06"},{"lineNumber":9,"author":{"gitId":"yuhengr"},"content":"","lastModifiedDate":"2024-03-06"},{"lineNumber":10,"author":{"gitId":"yuhengr"},"content":"    private int taskCount \u003d 0;","lastModifiedDate":"2024-03-06"},{"lineNumber":11,"author":{"gitId":"yuhengr"},"content":"    private ArrayList\u003cTask\u003e tasks;","lastModifiedDate":"2024-03-06"},{"lineNumber":12,"author":{"gitId":"yuhengr"},"content":"","lastModifiedDate":"2024-03-06"},{"lineNumber":13,"author":{"gitId":"yuhengr"},"content":"    public TaskList() {","lastModifiedDate":"2024-03-06"},{"lineNumber":14,"author":{"gitId":"yuhengr"},"content":"        this.tasks \u003d new ArrayList\u003cTask\u003e();","lastModifiedDate":"2024-03-06"},{"lineNumber":15,"author":{"gitId":"yuhengr"},"content":"    }","lastModifiedDate":"2024-03-06"},{"lineNumber":16,"author":{"gitId":"yuhengr"},"content":"","lastModifiedDate":"2024-03-06"},{"lineNumber":17,"author":{"gitId":"yuhengr"},"content":"    public int getTaskCount() {","lastModifiedDate":"2024-03-07"},{"lineNumber":18,"author":{"gitId":"yuhengr"},"content":"        return this.taskCount;","lastModifiedDate":"2024-03-06"},{"lineNumber":19,"author":{"gitId":"yuhengr"},"content":"    }","lastModifiedDate":"2024-03-06"},{"lineNumber":20,"author":{"gitId":"yuhengr"},"content":"","lastModifiedDate":"2024-03-06"},{"lineNumber":21,"author":{"gitId":"yuhengr"},"content":"    public Task getTask(int index) {","lastModifiedDate":"2024-03-07"},{"lineNumber":22,"author":{"gitId":"yuhengr"},"content":"        return tasks.get(index);","lastModifiedDate":"2024-03-07"},{"lineNumber":23,"author":{"gitId":"yuhengr"},"content":"    }","lastModifiedDate":"2024-03-07"},{"lineNumber":24,"author":{"gitId":"yuhengr"},"content":"","lastModifiedDate":"2024-03-07"},{"lineNumber":25,"author":{"gitId":"yuhengr"},"content":"    public void addTodo(String userInput) {","lastModifiedDate":"2024-03-06"},{"lineNumber":26,"author":{"gitId":"yuhengr"},"content":"        try {","lastModifiedDate":"2024-03-06"},{"lineNumber":27,"author":{"gitId":"yuhengr"},"content":"            tasks.add(Parser.parseTodo(userInput));","lastModifiedDate":"2024-03-08"},{"lineNumber":28,"author":{"gitId":"yuhengr"},"content":"            System.out.println(UI.TASK_ADDED_MESSAGE);","lastModifiedDate":"2024-03-07"},{"lineNumber":29,"author":{"gitId":"yuhengr"},"content":"            System.out.println(tasks.get(taskCount));","lastModifiedDate":"2024-03-06"},{"lineNumber":30,"author":{"gitId":"yuhengr"},"content":"            taskCount++;","lastModifiedDate":"2024-03-06"},{"lineNumber":31,"author":{"gitId":"yuhengr"},"content":"            UI.showTaskCountMessage(taskCount);","lastModifiedDate":"2024-03-07"},{"lineNumber":32,"author":{"gitId":"yuhengr"},"content":"        }","lastModifiedDate":"2024-03-07"},{"lineNumber":33,"author":{"gitId":"yuhengr"},"content":"        catch (EkudException error) {","lastModifiedDate":"2024-03-06"},{"lineNumber":34,"author":{"gitId":"yuhengr"},"content":"            System.out.println(UI.TODO_FORMAT_ERROR_MESSAGE);","lastModifiedDate":"2024-03-08"},{"lineNumber":35,"author":{"gitId":"yuhengr"},"content":"        }","lastModifiedDate":"2024-03-06"},{"lineNumber":36,"author":{"gitId":"yuhengr"},"content":"    }","lastModifiedDate":"2024-03-06"},{"lineNumber":37,"author":{"gitId":"yuhengr"},"content":"","lastModifiedDate":"2024-03-06"},{"lineNumber":38,"author":{"gitId":"yuhengr"},"content":"    public void addDeadline(String userInput) {","lastModifiedDate":"2024-03-06"},{"lineNumber":39,"author":{"gitId":"yuhengr"},"content":"        try {","lastModifiedDate":"2024-03-06"},{"lineNumber":40,"author":{"gitId":"yuhengr"},"content":"            tasks.add(Parser.parseDeadline(userInput));","lastModifiedDate":"2024-03-08"},{"lineNumber":41,"author":{"gitId":"yuhengr"},"content":"                System.out.println(UI.TASK_ADDED_MESSAGE);","lastModifiedDate":"2024-03-07"},{"lineNumber":42,"author":{"gitId":"yuhengr"},"content":"                System.out.println(tasks.get(taskCount));","lastModifiedDate":"2024-03-06"},{"lineNumber":43,"author":{"gitId":"yuhengr"},"content":"                taskCount++;","lastModifiedDate":"2024-03-06"},{"lineNumber":44,"author":{"gitId":"yuhengr"},"content":"                UI.showTaskCountMessage(taskCount);","lastModifiedDate":"2024-03-07"},{"lineNumber":45,"author":{"gitId":"yuhengr"},"content":"        }","lastModifiedDate":"2024-03-07"},{"lineNumber":46,"author":{"gitId":"yuhengr"},"content":"        catch (EkudException error) {","lastModifiedDate":"2024-03-06"},{"lineNumber":47,"author":{"gitId":"yuhengr"},"content":"            System.out.println(UI.DEADLINE_ERROR_MESSAGE);","lastModifiedDate":"2024-03-08"},{"lineNumber":48,"author":{"gitId":"yuhengr"},"content":"        }","lastModifiedDate":"2024-03-08"},{"lineNumber":49,"author":{"gitId":"yuhengr"},"content":"        catch (IndexOutOfBoundsException error) {","lastModifiedDate":"2024-03-08"},{"lineNumber":50,"author":{"gitId":"yuhengr"},"content":"            System.out.println(UI.DEADLINE_FORMAT_ERROR_MESSAGE);","lastModifiedDate":"2024-03-08"},{"lineNumber":51,"author":{"gitId":"yuhengr"},"content":"        }","lastModifiedDate":"2024-03-06"},{"lineNumber":52,"author":{"gitId":"yuhengr"},"content":"    };","lastModifiedDate":"2024-03-06"},{"lineNumber":53,"author":{"gitId":"yuhengr"},"content":"","lastModifiedDate":"2024-03-06"},{"lineNumber":54,"author":{"gitId":"yuhengr"},"content":"    public void addEvent(String userInput) {","lastModifiedDate":"2024-03-06"},{"lineNumber":55,"author":{"gitId":"yuhengr"},"content":"        try {","lastModifiedDate":"2024-03-06"},{"lineNumber":56,"author":{"gitId":"yuhengr"},"content":"            tasks.add(Parser.parseEvent(userInput));","lastModifiedDate":"2024-03-08"},{"lineNumber":57,"author":{"gitId":"yuhengr"},"content":"            System.out.println(UI.TASK_ADDED_MESSAGE);","lastModifiedDate":"2024-03-07"},{"lineNumber":58,"author":{"gitId":"yuhengr"},"content":"            System.out.println(tasks.get(taskCount));","lastModifiedDate":"2024-03-06"},{"lineNumber":59,"author":{"gitId":"yuhengr"},"content":"            taskCount++;","lastModifiedDate":"2024-03-06"},{"lineNumber":60,"author":{"gitId":"yuhengr"},"content":"            UI.showTaskCountMessage(taskCount);","lastModifiedDate":"2024-03-07"},{"lineNumber":61,"author":{"gitId":"yuhengr"},"content":"        }","lastModifiedDate":"2024-03-07"},{"lineNumber":62,"author":{"gitId":"yuhengr"},"content":"        catch (EkudException error) {","lastModifiedDate":"2024-03-06"},{"lineNumber":63,"author":{"gitId":"yuhengr"},"content":"            System.out.println(UI.EVENT_ERROR_MESSAGE);","lastModifiedDate":"2024-03-08"},{"lineNumber":64,"author":{"gitId":"yuhengr"},"content":"        }","lastModifiedDate":"2024-03-08"},{"lineNumber":65,"author":{"gitId":"yuhengr"},"content":"        catch (IndexOutOfBoundsException error) {","lastModifiedDate":"2024-03-08"},{"lineNumber":66,"author":{"gitId":"yuhengr"},"content":"            System.out.println(UI.EVENT_FORMAT_ERROR_MESSAGE);","lastModifiedDate":"2024-03-08"},{"lineNumber":67,"author":{"gitId":"yuhengr"},"content":"        }","lastModifiedDate":"2024-03-06"},{"lineNumber":68,"author":{"gitId":"yuhengr"},"content":"    };","lastModifiedDate":"2024-03-06"},{"lineNumber":69,"author":{"gitId":"yuhengr"},"content":"","lastModifiedDate":"2024-03-06"},{"lineNumber":70,"author":{"gitId":"yuhengr"},"content":"    public void list() {","lastModifiedDate":"2024-03-06"},{"lineNumber":71,"author":{"gitId":"yuhengr"},"content":"        System.out.println(UI.LIST_TASK_MESSAGE);","lastModifiedDate":"2024-03-07"},{"lineNumber":72,"author":{"gitId":"yuhengr"},"content":"        for(int i \u003d 0; i \u003c taskCount; i++){","lastModifiedDate":"2024-03-06"},{"lineNumber":73,"author":{"gitId":"yuhengr"},"content":"            System.out.println((i + 1) + \".\" + tasks.get(i));","lastModifiedDate":"2024-03-06"},{"lineNumber":74,"author":{"gitId":"yuhengr"},"content":"        }","lastModifiedDate":"2024-03-06"},{"lineNumber":75,"author":{"gitId":"yuhengr"},"content":"    }","lastModifiedDate":"2024-03-06"},{"lineNumber":76,"author":{"gitId":"yuhengr"},"content":"","lastModifiedDate":"2024-03-06"},{"lineNumber":77,"author":{"gitId":"yuhengr"},"content":"    public void delete(String userInput) {","lastModifiedDate":"2024-03-06"},{"lineNumber":78,"author":{"gitId":"yuhengr"},"content":"        String[] userInputWords \u003d userInput.split(\" \");","lastModifiedDate":"2024-03-06"},{"lineNumber":79,"author":{"gitId":"yuhengr"},"content":"        try {","lastModifiedDate":"2024-03-06"},{"lineNumber":80,"author":{"gitId":"yuhengr"},"content":"            if(userInputWords.length \u003d\u003d 1 || Integer.parseInt(userInputWords[1]) \u003e taskCount){","lastModifiedDate":"2024-03-06"},{"lineNumber":81,"author":{"gitId":"yuhengr"},"content":"                throw new EkudException();","lastModifiedDate":"2024-03-06"},{"lineNumber":82,"author":{"gitId":"yuhengr"},"content":"            }","lastModifiedDate":"2024-03-06"},{"lineNumber":83,"author":{"gitId":"yuhengr"},"content":"            else{","lastModifiedDate":"2024-03-06"},{"lineNumber":84,"author":{"gitId":"yuhengr"},"content":"                int taskIndex \u003d Integer.parseInt(userInputWords[1]) - 1;","lastModifiedDate":"2024-03-06"},{"lineNumber":85,"author":{"gitId":"yuhengr"},"content":"                System.out.println(UI.DELETE_TASK_MESSAGE);","lastModifiedDate":"2024-03-07"},{"lineNumber":86,"author":{"gitId":"yuhengr"},"content":"                System.out.println(tasks.get(taskIndex));","lastModifiedDate":"2024-03-06"},{"lineNumber":87,"author":{"gitId":"yuhengr"},"content":"                tasks.remove(taskIndex);","lastModifiedDate":"2024-03-06"},{"lineNumber":88,"author":{"gitId":"yuhengr"},"content":"                taskCount--;","lastModifiedDate":"2024-03-06"},{"lineNumber":89,"author":{"gitId":"yuhengr"},"content":"                UI.showTaskCountMessage(taskCount);","lastModifiedDate":"2024-03-07"},{"lineNumber":90,"author":{"gitId":"yuhengr"},"content":"            }","lastModifiedDate":"2024-03-06"},{"lineNumber":91,"author":{"gitId":"yuhengr"},"content":"        }","lastModifiedDate":"2024-03-06"},{"lineNumber":92,"author":{"gitId":"yuhengr"},"content":"        catch(EkudException error){","lastModifiedDate":"2024-03-06"},{"lineNumber":93,"author":{"gitId":"yuhengr"},"content":"            System.out.println(UI.INVALID_TASK_NUM_MESSAGE);","lastModifiedDate":"2024-03-07"},{"lineNumber":94,"author":{"gitId":"yuhengr"},"content":"        }","lastModifiedDate":"2024-03-06"},{"lineNumber":95,"author":{"gitId":"yuhengr"},"content":"    }","lastModifiedDate":"2024-03-06"},{"lineNumber":96,"author":{"gitId":"yuhengr"},"content":"","lastModifiedDate":"2024-03-06"},{"lineNumber":97,"author":{"gitId":"yuhengr"},"content":"    public void mark(String userInput) {","lastModifiedDate":"2024-03-06"},{"lineNumber":98,"author":{"gitId":"yuhengr"},"content":"        String[] userInputWords \u003d userInput.split(\" \");","lastModifiedDate":"2024-03-06"},{"lineNumber":99,"author":{"gitId":"yuhengr"},"content":"        try {","lastModifiedDate":"2024-03-06"},{"lineNumber":100,"author":{"gitId":"yuhengr"},"content":"            if (userInputWords.length \u003d\u003d 1 || Integer.parseInt(userInputWords[1]) \u003e taskCount){","lastModifiedDate":"2024-03-06"},{"lineNumber":101,"author":{"gitId":"yuhengr"},"content":"                throw new EkudException();","lastModifiedDate":"2024-03-06"},{"lineNumber":102,"author":{"gitId":"yuhengr"},"content":"            }","lastModifiedDate":"2024-03-06"},{"lineNumber":103,"author":{"gitId":"yuhengr"},"content":"            else {","lastModifiedDate":"2024-03-06"},{"lineNumber":104,"author":{"gitId":"yuhengr"},"content":"                int taskIndex \u003d Integer.parseInt(userInputWords[1]) - 1;","lastModifiedDate":"2024-03-06"},{"lineNumber":105,"author":{"gitId":"yuhengr"},"content":"                tasks.get(taskIndex).markAsDone();","lastModifiedDate":"2024-03-06"},{"lineNumber":106,"author":{"gitId":"yuhengr"},"content":"                System.out.println(UI.MARK_TASK_MESSAGE);","lastModifiedDate":"2024-03-07"},{"lineNumber":107,"author":{"gitId":"yuhengr"},"content":"                System.out.println(tasks.get(taskIndex));","lastModifiedDate":"2024-03-06"},{"lineNumber":108,"author":{"gitId":"yuhengr"},"content":"            }","lastModifiedDate":"2024-03-06"},{"lineNumber":109,"author":{"gitId":"yuhengr"},"content":"        }","lastModifiedDate":"2024-03-06"},{"lineNumber":110,"author":{"gitId":"yuhengr"},"content":"        catch (EkudException error) {","lastModifiedDate":"2024-03-06"},{"lineNumber":111,"author":{"gitId":"yuhengr"},"content":"            System.out.println(UI.INVALID_TASK_NUM_MESSAGE);","lastModifiedDate":"2024-03-07"},{"lineNumber":112,"author":{"gitId":"yuhengr"},"content":"        }","lastModifiedDate":"2024-03-06"},{"lineNumber":113,"author":{"gitId":"yuhengr"},"content":"    }","lastModifiedDate":"2024-03-06"},{"lineNumber":114,"author":{"gitId":"yuhengr"},"content":"","lastModifiedDate":"2024-03-06"},{"lineNumber":115,"author":{"gitId":"yuhengr"},"content":"    public void unmark(String userInput) {","lastModifiedDate":"2024-03-06"},{"lineNumber":116,"author":{"gitId":"yuhengr"},"content":"        String[] userInputWords \u003d userInput.split(\" \");","lastModifiedDate":"2024-03-06"},{"lineNumber":117,"author":{"gitId":"yuhengr"},"content":"        try {","lastModifiedDate":"2024-03-06"},{"lineNumber":118,"author":{"gitId":"yuhengr"},"content":"            if (userInputWords.length \u003d\u003d 1 || Integer.parseInt(userInputWords[1]) \u003e taskCount){","lastModifiedDate":"2024-03-06"},{"lineNumber":119,"author":{"gitId":"yuhengr"},"content":"                throw new EkudException();","lastModifiedDate":"2024-03-06"},{"lineNumber":120,"author":{"gitId":"yuhengr"},"content":"            }","lastModifiedDate":"2024-03-06"},{"lineNumber":121,"author":{"gitId":"yuhengr"},"content":"            else {","lastModifiedDate":"2024-03-06"},{"lineNumber":122,"author":{"gitId":"yuhengr"},"content":"                int taskIndex \u003d Integer.parseInt(userInputWords[1]) - 1;","lastModifiedDate":"2024-03-06"},{"lineNumber":123,"author":{"gitId":"yuhengr"},"content":"                tasks.get(taskIndex).markAsNotDone();","lastModifiedDate":"2024-03-06"},{"lineNumber":124,"author":{"gitId":"yuhengr"},"content":"                System.out.println(UI.UNMARK_TASK_MESSAGE);","lastModifiedDate":"2024-03-07"},{"lineNumber":125,"author":{"gitId":"yuhengr"},"content":"                System.out.println(tasks.get(taskIndex));","lastModifiedDate":"2024-03-06"},{"lineNumber":126,"author":{"gitId":"yuhengr"},"content":"            }","lastModifiedDate":"2024-03-06"},{"lineNumber":127,"author":{"gitId":"yuhengr"},"content":"        }","lastModifiedDate":"2024-03-06"},{"lineNumber":128,"author":{"gitId":"yuhengr"},"content":"        catch (EkudException error) {","lastModifiedDate":"2024-03-06"},{"lineNumber":129,"author":{"gitId":"yuhengr"},"content":"            System.out.println(UI.INVALID_TASK_NUM_MESSAGE);","lastModifiedDate":"2024-03-07"},{"lineNumber":130,"author":{"gitId":"yuhengr"},"content":"        }","lastModifiedDate":"2024-03-06"},{"lineNumber":131,"author":{"gitId":"yuhengr"},"content":"    }","lastModifiedDate":"2024-03-06"},{"lineNumber":132,"author":{"gitId":"yuhengr"},"content":"","lastModifiedDate":"2024-03-06"},{"lineNumber":133,"author":{"gitId":"yuhengr"},"content":"    public void find(String userInput) {","lastModifiedDate":"2024-03-08"},{"lineNumber":134,"author":{"gitId":"yuhengr"},"content":"        String[] userInputWords \u003d userInput.split(\" \");","lastModifiedDate":"2024-03-08"},{"lineNumber":135,"author":{"gitId":"yuhengr"},"content":"        ArrayList\u003cTask\u003e relevantTasks \u003d new ArrayList\u003cTask\u003e();","lastModifiedDate":"2024-03-08"},{"lineNumber":136,"author":{"gitId":"yuhengr"},"content":"","lastModifiedDate":"2024-03-08"},{"lineNumber":137,"author":{"gitId":"yuhengr"},"content":"        try {","lastModifiedDate":"2024-03-08"},{"lineNumber":138,"author":{"gitId":"yuhengr"},"content":"            if(userInputWords.length \u003c\u003d 1) {","lastModifiedDate":"2024-03-08"},{"lineNumber":139,"author":{"gitId":"yuhengr"},"content":"                throw new EkudException();","lastModifiedDate":"2024-03-08"},{"lineNumber":140,"author":{"gitId":"yuhengr"},"content":"            }","lastModifiedDate":"2024-03-08"},{"lineNumber":141,"author":{"gitId":"yuhengr"},"content":"            else {","lastModifiedDate":"2024-03-08"},{"lineNumber":142,"author":{"gitId":"yuhengr"},"content":"                String keyword \u003d userInputWords[1].toLowerCase();","lastModifiedDate":"2024-03-08"},{"lineNumber":143,"author":{"gitId":"yuhengr"},"content":"","lastModifiedDate":"2024-03-08"},{"lineNumber":144,"author":{"gitId":"yuhengr"},"content":"                for(int i \u003d 0; i \u003c taskCount; i++) {","lastModifiedDate":"2024-03-08"},{"lineNumber":145,"author":{"gitId":"yuhengr"},"content":"                    String currentTask \u003d tasks.get(i).toString().toLowerCase();","lastModifiedDate":"2024-03-08"},{"lineNumber":146,"author":{"gitId":"yuhengr"},"content":"                    if(currentTask.contains(keyword)) {","lastModifiedDate":"2024-03-08"},{"lineNumber":147,"author":{"gitId":"yuhengr"},"content":"                        relevantTasks.add(tasks.get(i));","lastModifiedDate":"2024-03-08"},{"lineNumber":148,"author":{"gitId":"yuhengr"},"content":"                    }","lastModifiedDate":"2024-03-08"},{"lineNumber":149,"author":{"gitId":"yuhengr"},"content":"                }","lastModifiedDate":"2024-03-08"},{"lineNumber":150,"author":{"gitId":"yuhengr"},"content":"                System.out.println(UI.FIND_RESULT_MESSAGE);","lastModifiedDate":"2024-03-08"},{"lineNumber":151,"author":{"gitId":"yuhengr"},"content":"","lastModifiedDate":"2024-03-08"},{"lineNumber":152,"author":{"gitId":"yuhengr"},"content":"                for(int i \u003d 0; i \u003c relevantTasks.size(); i++) {","lastModifiedDate":"2024-03-08"},{"lineNumber":153,"author":{"gitId":"yuhengr"},"content":"                    System.out.println((i + 1) + \".\" + relevantTasks.get(i));","lastModifiedDate":"2024-03-08"},{"lineNumber":154,"author":{"gitId":"yuhengr"},"content":"                }","lastModifiedDate":"2024-03-08"},{"lineNumber":155,"author":{"gitId":"yuhengr"},"content":"            }","lastModifiedDate":"2024-03-08"},{"lineNumber":156,"author":{"gitId":"yuhengr"},"content":"        }","lastModifiedDate":"2024-03-08"},{"lineNumber":157,"author":{"gitId":"yuhengr"},"content":"        catch (EkudException error) {","lastModifiedDate":"2024-03-08"},{"lineNumber":158,"author":{"gitId":"yuhengr"},"content":"            System.out.println(UI.FIND_ERROR_MESSAGE);","lastModifiedDate":"2024-03-08"},{"lineNumber":159,"author":{"gitId":"yuhengr"},"content":"        }","lastModifiedDate":"2024-03-08"},{"lineNumber":160,"author":{"gitId":"yuhengr"},"content":"    }","lastModifiedDate":"2024-03-08"},{"lineNumber":161,"author":{"gitId":"yuhengr"},"content":"","lastModifiedDate":"2024-03-08"},{"lineNumber":162,"author":{"gitId":"yuhengr"},"content":"    public void addTaskFromFile(String currentLine) {","lastModifiedDate":"2024-03-07"},{"lineNumber":163,"author":{"gitId":"yuhengr"},"content":"        if(currentLine.contains(\"[T]\")){","lastModifiedDate":"2024-03-07"},{"lineNumber":164,"author":{"gitId":"yuhengr"},"content":"            int descriptionStart \u003d currentLine.indexOf(\"[T]\") + 7;","lastModifiedDate":"2024-03-07"},{"lineNumber":165,"author":{"gitId":"yuhengr"},"content":"            tasks.add(new Todo(currentLine.substring(descriptionStart)));","lastModifiedDate":"2024-03-07"},{"lineNumber":166,"author":{"gitId":"yuhengr"},"content":"            taskCount++;","lastModifiedDate":"2024-03-07"},{"lineNumber":167,"author":{"gitId":"yuhengr"},"content":"        }","lastModifiedDate":"2024-03-07"},{"lineNumber":168,"author":{"gitId":"yuhengr"},"content":"        else if (currentLine.contains(\"[D]\")){","lastModifiedDate":"2024-03-07"},{"lineNumber":169,"author":{"gitId":"yuhengr"},"content":"            int descriptionStart \u003d currentLine.indexOf(\"[D]\") + 7;","lastModifiedDate":"2024-03-07"},{"lineNumber":170,"author":{"gitId":"yuhengr"},"content":"            int descriptionEnd \u003d currentLine.indexOf(\"(by:\") - 1;","lastModifiedDate":"2024-03-07"},{"lineNumber":171,"author":{"gitId":"yuhengr"},"content":"            int byStart \u003d currentLine.indexOf(\"(by:\") + 5;","lastModifiedDate":"2024-03-07"},{"lineNumber":172,"author":{"gitId":"yuhengr"},"content":"            int byEnd \u003d currentLine.indexOf(\u0027)\u0027, byStart);","lastModifiedDate":"2024-03-07"},{"lineNumber":173,"author":{"gitId":"yuhengr"},"content":"            tasks.add(new Deadline(currentLine.substring(descriptionStart, descriptionEnd),","lastModifiedDate":"2024-03-07"},{"lineNumber":174,"author":{"gitId":"yuhengr"},"content":"                    currentLine.substring(byStart, byEnd)));","lastModifiedDate":"2024-03-07"},{"lineNumber":175,"author":{"gitId":"yuhengr"},"content":"            taskCount++;","lastModifiedDate":"2024-03-07"},{"lineNumber":176,"author":{"gitId":"yuhengr"},"content":"        }","lastModifiedDate":"2024-03-07"},{"lineNumber":177,"author":{"gitId":"yuhengr"},"content":"        else if (currentLine.contains(\"[E]\")){","lastModifiedDate":"2024-03-07"},{"lineNumber":178,"author":{"gitId":"yuhengr"},"content":"            int descriptionStart \u003d currentLine.indexOf(\"[E]\") + 7;","lastModifiedDate":"2024-03-07"},{"lineNumber":179,"author":{"gitId":"yuhengr"},"content":"            int descriptionEnd \u003d currentLine.indexOf(\"(from:\") - 1;","lastModifiedDate":"2024-03-07"},{"lineNumber":180,"author":{"gitId":"yuhengr"},"content":"            int fromStart \u003d currentLine.indexOf(\"(from:\") + 7;","lastModifiedDate":"2024-03-07"},{"lineNumber":181,"author":{"gitId":"yuhengr"},"content":"            int fromEnd \u003d currentLine.indexOf(\"to:\") - 1;","lastModifiedDate":"2024-03-07"},{"lineNumber":182,"author":{"gitId":"yuhengr"},"content":"            int toStart \u003d currentLine.indexOf(\"to:\") + 4;","lastModifiedDate":"2024-03-07"},{"lineNumber":183,"author":{"gitId":"yuhengr"},"content":"            int toEnd \u003d currentLine.indexOf(\u0027)\u0027, toStart);","lastModifiedDate":"2024-03-07"},{"lineNumber":184,"author":{"gitId":"yuhengr"},"content":"            tasks.add(new Event(currentLine.substring(descriptionStart, descriptionEnd),","lastModifiedDate":"2024-03-07"},{"lineNumber":185,"author":{"gitId":"yuhengr"},"content":"                    currentLine.substring(fromStart, fromEnd),","lastModifiedDate":"2024-03-07"},{"lineNumber":186,"author":{"gitId":"yuhengr"},"content":"                    currentLine.substring(toStart, toEnd)));","lastModifiedDate":"2024-03-07"},{"lineNumber":187,"author":{"gitId":"yuhengr"},"content":"            taskCount++;","lastModifiedDate":"2024-03-07"},{"lineNumber":188,"author":{"gitId":"yuhengr"},"content":"        }","lastModifiedDate":"2024-03-07"},{"lineNumber":189,"author":{"gitId":"yuhengr"},"content":"    }","lastModifiedDate":"2024-03-07"},{"lineNumber":190,"author":{"gitId":"yuhengr"},"content":"","lastModifiedDate":"2024-03-07"},{"lineNumber":191,"author":{"gitId":"yuhengr"},"content":"}","lastModifiedDate":"2024-03-06"}],"authorContributionMap":{"yuhengr":191}},{"path":"src/main/java/task/Todo.java","fileType":"java","lines":[{"lineNumber":1,"author":{"gitId":"yuhengr"},"content":"package task;","lastModifiedDate":"2024-03-06"},{"lineNumber":2,"author":{"gitId":"yuhengr"},"content":"","lastModifiedDate":"2024-03-06"},{"lineNumber":3,"author":{"gitId":"yuhengr"},"content":"public class Todo extends Task{","lastModifiedDate":"2024-02-09"},{"lineNumber":4,"author":{"gitId":"yuhengr"},"content":"","lastModifiedDate":"2024-02-09"},{"lineNumber":5,"author":{"gitId":"yuhengr"},"content":"    public Todo(String description) {","lastModifiedDate":"2024-02-09"},{"lineNumber":6,"author":{"gitId":"yuhengr"},"content":"        super(description);","lastModifiedDate":"2024-02-09"},{"lineNumber":7,"author":{"gitId":"yuhengr"},"content":"    }","lastModifiedDate":"2024-02-09"},{"lineNumber":8,"author":{"gitId":"yuhengr"},"content":"","lastModifiedDate":"2024-02-09"},{"lineNumber":9,"author":{"gitId":"yuhengr"},"content":"    public String toString() {","lastModifiedDate":"2024-02-09"},{"lineNumber":10,"author":{"gitId":"yuhengr"},"content":"        return \"[T]\" + super.toString();","lastModifiedDate":"2024-02-09"},{"lineNumber":11,"author":{"gitId":"yuhengr"},"content":"    }","lastModifiedDate":"2024-02-09"},{"lineNumber":12,"author":{"gitId":"yuhengr"},"content":"}","lastModifiedDate":"2024-02-09"}],"authorContributionMap":{"yuhengr":12}},{"path":"src/main/java/ui/Parser.java","fileType":"java","lines":[{"lineNumber":1,"author":{"gitId":"yuhengr"},"content":"package ui;","lastModifiedDate":"2024-03-08"},{"lineNumber":2,"author":{"gitId":"yuhengr"},"content":"","lastModifiedDate":"2024-03-08"},{"lineNumber":3,"author":{"gitId":"yuhengr"},"content":"import exception.EkudException;","lastModifiedDate":"2024-03-08"},{"lineNumber":4,"author":{"gitId":"yuhengr"},"content":"import task.Task;","lastModifiedDate":"2024-03-08"},{"lineNumber":5,"author":{"gitId":"yuhengr"},"content":"import task.Todo;","lastModifiedDate":"2024-03-08"},{"lineNumber":6,"author":{"gitId":"yuhengr"},"content":"import task.Deadline;","lastModifiedDate":"2024-03-08"},{"lineNumber":7,"author":{"gitId":"yuhengr"},"content":"import task.Event;","lastModifiedDate":"2024-03-08"},{"lineNumber":8,"author":{"gitId":"yuhengr"},"content":"","lastModifiedDate":"2024-03-08"},{"lineNumber":9,"author":{"gitId":"yuhengr"},"content":"public class Parser {","lastModifiedDate":"2024-03-08"},{"lineNumber":10,"author":{"gitId":"yuhengr"},"content":"","lastModifiedDate":"2024-03-08"},{"lineNumber":11,"author":{"gitId":"yuhengr"},"content":"    public static Todo parseTodo(String userInput) throws EkudException {","lastModifiedDate":"2024-03-08"},{"lineNumber":12,"author":{"gitId":"yuhengr"},"content":"","lastModifiedDate":"2024-03-08"},{"lineNumber":13,"author":{"gitId":"yuhengr"},"content":"        int dividerPosition \u003d userInput.indexOf(\" \");","lastModifiedDate":"2024-03-08"},{"lineNumber":14,"author":{"gitId":"yuhengr"},"content":"        if(dividerPosition \u003d\u003d -1) {","lastModifiedDate":"2024-03-08"},{"lineNumber":15,"author":{"gitId":"yuhengr"},"content":"            throw new EkudException();","lastModifiedDate":"2024-03-08"},{"lineNumber":16,"author":{"gitId":"yuhengr"},"content":"        }","lastModifiedDate":"2024-03-08"},{"lineNumber":17,"author":{"gitId":"yuhengr"},"content":"        int descriptionStart \u003d dividerPosition + 1;","lastModifiedDate":"2024-03-08"},{"lineNumber":18,"author":{"gitId":"yuhengr"},"content":"        return new Todo(userInput.substring(descriptionStart).trim());","lastModifiedDate":"2024-03-08"},{"lineNumber":19,"author":{"gitId":"yuhengr"},"content":"    }","lastModifiedDate":"2024-03-08"},{"lineNumber":20,"author":{"gitId":"yuhengr"},"content":"","lastModifiedDate":"2024-03-08"},{"lineNumber":21,"author":{"gitId":"yuhengr"},"content":"    public static Deadline parseDeadline(String userInput) throws EkudException, IndexOutOfBoundsException {","lastModifiedDate":"2024-03-08"},{"lineNumber":22,"author":{"gitId":"yuhengr"},"content":"","lastModifiedDate":"2024-03-08"},{"lineNumber":23,"author":{"gitId":"yuhengr"},"content":"        int dividerPosition \u003d userInput.indexOf(\" \");","lastModifiedDate":"2024-03-08"},{"lineNumber":24,"author":{"gitId":"yuhengr"},"content":"        int slashPosition \u003d userInput.indexOf(\"/by\");","lastModifiedDate":"2024-03-08"},{"lineNumber":25,"author":{"gitId":"yuhengr"},"content":"        int descriptionStart \u003d dividerPosition + 1;","lastModifiedDate":"2024-03-08"},{"lineNumber":26,"author":{"gitId":"yuhengr"},"content":"        int descriptionEnd \u003d slashPosition - 1;","lastModifiedDate":"2024-03-08"},{"lineNumber":27,"author":{"gitId":"yuhengr"},"content":"        int byStart \u003d slashPosition + 4;","lastModifiedDate":"2024-03-08"},{"lineNumber":28,"author":{"gitId":"yuhengr"},"content":"        return new Deadline(userInput.substring(descriptionStart, descriptionEnd).trim(),","lastModifiedDate":"2024-03-08"},{"lineNumber":29,"author":{"gitId":"yuhengr"},"content":"                userInput.substring(byStart).trim());","lastModifiedDate":"2024-03-08"},{"lineNumber":30,"author":{"gitId":"yuhengr"},"content":"    }","lastModifiedDate":"2024-03-08"},{"lineNumber":31,"author":{"gitId":"yuhengr"},"content":"","lastModifiedDate":"2024-03-08"},{"lineNumber":32,"author":{"gitId":"yuhengr"},"content":"    public static Event parseEvent(String userInput) throws EkudException, IndexOutOfBoundsException {","lastModifiedDate":"2024-03-08"},{"lineNumber":33,"author":{"gitId":"yuhengr"},"content":"","lastModifiedDate":"2024-03-08"},{"lineNumber":34,"author":{"gitId":"yuhengr"},"content":"        int dividerPosition \u003d userInput.indexOf(\" \");","lastModifiedDate":"2024-03-08"},{"lineNumber":35,"author":{"gitId":"yuhengr"},"content":"        int descriptionStart \u003d dividerPosition + 1;","lastModifiedDate":"2024-03-08"},{"lineNumber":36,"author":{"gitId":"yuhengr"},"content":"        int descriptionEnd \u003d userInput.indexOf(\"/from\") - 1;","lastModifiedDate":"2024-03-08"},{"lineNumber":37,"author":{"gitId":"yuhengr"},"content":"        int fromStart \u003d userInput.indexOf(\"/from\") + 6;","lastModifiedDate":"2024-03-08"},{"lineNumber":38,"author":{"gitId":"yuhengr"},"content":"        int fromEnd \u003d userInput.indexOf(\"/to\") - 1;","lastModifiedDate":"2024-03-08"},{"lineNumber":39,"author":{"gitId":"yuhengr"},"content":"        int toStart \u003d userInput.indexOf(\"/to\") + 4;","lastModifiedDate":"2024-03-08"},{"lineNumber":40,"author":{"gitId":"yuhengr"},"content":"","lastModifiedDate":"2024-03-08"},{"lineNumber":41,"author":{"gitId":"yuhengr"},"content":"        return new Event(userInput.substring(descriptionStart, descriptionEnd).trim(),","lastModifiedDate":"2024-03-08"},{"lineNumber":42,"author":{"gitId":"yuhengr"},"content":"                userInput.substring(fromStart, fromEnd).trim(),","lastModifiedDate":"2024-03-08"},{"lineNumber":43,"author":{"gitId":"yuhengr"},"content":"                userInput.substring(toStart).trim());","lastModifiedDate":"2024-03-08"},{"lineNumber":44,"author":{"gitId":"yuhengr"},"content":"    }","lastModifiedDate":"2024-03-08"},{"lineNumber":45,"author":{"gitId":"yuhengr"},"content":"}","lastModifiedDate":"2024-03-08"}],"authorContributionMap":{"yuhengr":45}},{"path":"src/main/java/ui/UI.java","fileType":"java","lines":[{"lineNumber":1,"author":{"gitId":"yuhengr"},"content":"package ui;","lastModifiedDate":"2024-03-07"},{"lineNumber":2,"author":{"gitId":"yuhengr"},"content":"","lastModifiedDate":"2024-03-07"},{"lineNumber":3,"author":{"gitId":"yuhengr"},"content":"public class UI {","lastModifiedDate":"2024-03-07"},{"lineNumber":4,"author":{"gitId":"yuhengr"},"content":"","lastModifiedDate":"2024-03-07"},{"lineNumber":5,"author":{"gitId":"yuhengr"},"content":"    private static String LOGO \u003d \" ____        _        \\n\"","lastModifiedDate":"2024-03-07"},{"lineNumber":6,"author":{"gitId":"yuhengr"},"content":"            + \"|  _ \\\\ _   _| | _____ \\n\"","lastModifiedDate":"2024-03-07"},{"lineNumber":7,"author":{"gitId":"yuhengr"},"content":"            + \"| | | | | | | |/ / _ \\\\\\n\"","lastModifiedDate":"2024-03-07"},{"lineNumber":8,"author":{"gitId":"yuhengr"},"content":"            + \"| |_| | |_| |   \u003c  __/\\n\"","lastModifiedDate":"2024-03-07"},{"lineNumber":9,"author":{"gitId":"yuhengr"},"content":"            + \"|____/ \\\\__,_|_|\\\\_\\\\___|\\n\";","lastModifiedDate":"2024-03-07"},{"lineNumber":10,"author":{"gitId":"yuhengr"},"content":"","lastModifiedDate":"2024-03-07"},{"lineNumber":11,"author":{"gitId":"yuhengr"},"content":"    public static String GREETING_MESSAGE \u003d \"I\u0027m Ekud! What can I do for you?\";","lastModifiedDate":"2024-03-07"},{"lineNumber":12,"author":{"gitId":"yuhengr"},"content":"","lastModifiedDate":"2024-03-07"},{"lineNumber":13,"author":{"gitId":"yuhengr"},"content":"    public static String FILE_NOT_FOUND_MESSAGE \u003d \"File is not found. Tasks cannot be loaded.\";","lastModifiedDate":"2024-03-07"},{"lineNumber":14,"author":{"gitId":"yuhengr"},"content":"","lastModifiedDate":"2024-03-07"},{"lineNumber":15,"author":{"gitId":"yuhengr"},"content":"    public static String INVALID_COMMAND_MESSAGE \u003d \"That\u0027s not a valid command.\";","lastModifiedDate":"2024-03-07"},{"lineNumber":16,"author":{"gitId":"yuhengr"},"content":"","lastModifiedDate":"2024-03-07"},{"lineNumber":17,"author":{"gitId":"yuhengr"},"content":"    public static String FILE_WRITE_ERROR_MESSAGE \u003d \"Something went wrong when saving the tasks.\";","lastModifiedDate":"2024-03-07"},{"lineNumber":18,"author":{"gitId":"yuhengr"},"content":"","lastModifiedDate":"2024-03-07"},{"lineNumber":19,"author":{"gitId":"yuhengr"},"content":"    public static String TASK_ADDED_MESSAGE \u003d \"Got it. I\u0027ve added this task:\";","lastModifiedDate":"2024-03-07"},{"lineNumber":20,"author":{"gitId":"yuhengr"},"content":"","lastModifiedDate":"2024-03-07"},{"lineNumber":21,"author":{"gitId":"yuhengr"},"content":"    public static String TODO_FORMAT_ERROR_MESSAGE \u003d \"Invalid Todo format.\";","lastModifiedDate":"2024-03-08"},{"lineNumber":22,"author":{"gitId":"yuhengr"},"content":"","lastModifiedDate":"2024-03-07"},{"lineNumber":23,"author":{"gitId":"yuhengr"},"content":"    public static String DEADLINE_FORMAT_ERROR_MESSAGE \u003d \"Invalid Deadline format.\";","lastModifiedDate":"2024-03-08"},{"lineNumber":24,"author":{"gitId":"yuhengr"},"content":"","lastModifiedDate":"2024-03-07"},{"lineNumber":25,"author":{"gitId":"yuhengr"},"content":"    public static String DEADLINE_ERROR_MESSAGE \u003d \"Error. Unable to add Deadline.\";","lastModifiedDate":"2024-03-08"},{"lineNumber":26,"author":{"gitId":"yuhengr"},"content":"","lastModifiedDate":"2024-03-08"},{"lineNumber":27,"author":{"gitId":"yuhengr"},"content":"    public static String EVENT_FORMAT_ERROR_MESSAGE \u003d \"Invalid Event format.\";","lastModifiedDate":"2024-03-08"},{"lineNumber":28,"author":{"gitId":"yuhengr"},"content":"","lastModifiedDate":"2024-03-08"},{"lineNumber":29,"author":{"gitId":"yuhengr"},"content":"    public static String EVENT_ERROR_MESSAGE \u003d \"Error. Unable to add Event.\";","lastModifiedDate":"2024-03-08"},{"lineNumber":30,"author":{"gitId":"yuhengr"},"content":"","lastModifiedDate":"2024-03-07"},{"lineNumber":31,"author":{"gitId":"yuhengr"},"content":"    public static String INVALID_TASK_NUM_MESSAGE \u003d \"The task number is not valid or not provided.\";","lastModifiedDate":"2024-03-07"},{"lineNumber":32,"author":{"gitId":"yuhengr"},"content":"","lastModifiedDate":"2024-03-07"},{"lineNumber":33,"author":{"gitId":"yuhengr"},"content":"    public static String UNMARK_TASK_MESSAGE \u003d \"OK, I\u0027ve marked this task as not done yet:\";","lastModifiedDate":"2024-03-07"},{"lineNumber":34,"author":{"gitId":"yuhengr"},"content":"","lastModifiedDate":"2024-03-07"},{"lineNumber":35,"author":{"gitId":"yuhengr"},"content":"    public static String MARK_TASK_MESSAGE \u003d \"Nice! I\u0027ve marked this task as done:\";","lastModifiedDate":"2024-03-07"},{"lineNumber":36,"author":{"gitId":"yuhengr"},"content":"","lastModifiedDate":"2024-03-07"},{"lineNumber":37,"author":{"gitId":"yuhengr"},"content":"    public static String DELETE_TASK_MESSAGE \u003d \"Noted. I\u0027ve removed this task:\";","lastModifiedDate":"2024-03-07"},{"lineNumber":38,"author":{"gitId":"yuhengr"},"content":"","lastModifiedDate":"2024-03-07"},{"lineNumber":39,"author":{"gitId":"yuhengr"},"content":"    public static String LIST_TASK_MESSAGE \u003d \"Here are the tasks in your list:\";","lastModifiedDate":"2024-03-07"},{"lineNumber":40,"author":{"gitId":"yuhengr"},"content":"","lastModifiedDate":"2024-03-07"},{"lineNumber":41,"author":{"gitId":"yuhengr"},"content":"    public static String FIND_ERROR_MESSAGE \u003d \"Error searching for relevant tasks.\";","lastModifiedDate":"2024-03-08"},{"lineNumber":42,"author":{"gitId":"yuhengr"},"content":"","lastModifiedDate":"2024-03-08"},{"lineNumber":43,"author":{"gitId":"yuhengr"},"content":"    public static String FIND_RESULT_MESSAGE \u003d \"Here are the matching tasks in your list:\";","lastModifiedDate":"2024-03-08"},{"lineNumber":44,"author":{"gitId":"yuhengr"},"content":"","lastModifiedDate":"2024-03-08"},{"lineNumber":45,"author":{"gitId":"yuhengr"},"content":"    public static String EXIT_MESSAGE \u003d \"Goodbye. Hope to see you again soon.\";","lastModifiedDate":"2024-03-07"},{"lineNumber":46,"author":{"gitId":"yuhengr"},"content":"","lastModifiedDate":"2024-03-07"},{"lineNumber":47,"author":{"gitId":"yuhengr"},"content":"    public static void showTaskCountMessage(int taskCount) {","lastModifiedDate":"2024-03-07"},{"lineNumber":48,"author":{"gitId":"yuhengr"},"content":"        System.out.println(\"Now you have \" + taskCount + \" tasks in the list.\");","lastModifiedDate":"2024-03-07"},{"lineNumber":49,"author":{"gitId":"yuhengr"},"content":"    }","lastModifiedDate":"2024-03-07"},{"lineNumber":50,"author":{"gitId":"yuhengr"},"content":"}","lastModifiedDate":"2024-03-07"}],"authorContributionMap":{"yuhengr":50}}]
